langchain_qdrant/__init__.py
langchain_qdrant/_utils.py
langchain_qdrant/fastembed_sparse.py
langchain_qdrant/py.typed
langchain_qdrant/qdrant.py
langchain_qdrant/sparse_embeddings.py
langchain_qdrant/vectorstores.py
langchain_qdrant-1.0.0.dist-info/METADATA
langchain_qdrant-1.0.0.dist-info/WHEEL
langchain_qdrant-1.0.0.dist-info/licenses/LICENSE
langchain_qdrant-1.0.0.dist-info/RECORD
