Metadata-Version: 2.4
Name: langchain-qdrant
Version: 1.0.0
Summary: An integration package connecting Qdrant and LangChain
Project-URL: homepage, https://docs.langchain.com/oss/python/integrations/providers/qdrant
Project-URL: repository, https://github.com/langchain-ai/langchain/tree/master/libs/partners/qdrant
Project-URL: changelog, https://github.com/langchain-ai/langchain/releases?q=%22langchain-qdrant%22
Project-URL: docs, https://reference.langchain.com/python/integrations/langchain_qdrant/
Project-URL: twitter, https://x.com/LangChainAI
Project-URL: slack, https://www.langchain.com/join-community
Project-URL: reddit, https://www.reddit.com/r/LangChain/
License: MIT
License-File: LICENSE
Requires-Python: <4.0.0,>=3.10.0
Requires-Dist: langchain-core<2.0.0,>=1.0.0
Requires-Dist: pydantic<3.0.0,>=2.7.4
Requires-Dist: qdrant-client<2.0.0,>=1.10.1
Provides-Extra: fastembed
Requires-Dist: fastembed<1.0.0,>=0.3.3; (python_version < '3.13' and python_version >= '3.9') and extra == 'fastembed'
